{
    "$__mpe_config_竞技场": {
        "$__mpe_code": {
            "prefix": "",
            "coordinateMode": "absolute-v1",
            "savedViewport": {
                "x": 1294,
                "y": 88,
                "zoom": 0.76
            },
            "filename": "竞技场",
            "version": "v1.5.3"
        }
    },
    "进入竞技场选择开始": {
        "recognition": {
            "type": "OCR",
            "param": {
                "roi": [
                    1165,
                    371,
                    74,
                    34
                ],
                "expected": [
                    "竞技场"
                ]
            }
        },
        "action": {
            "type": "Click"
        },
        "post_delay": 5000,
        "next": [
            "检测是不是每周结算时间"
        ],
        "$__mpe_code": {
            "position": {
                "x": -1189,
                "y": 44
            }
        }
    },
    "进入新手竞技场": {
        "recognition": {
            "type": "OCR",
            "param": {
                "roi": [
                    289,
                    111,
                    159,
                    40
                ],
                "expected": [
                    "新手竞技场"
                ]
            }
        },
        "action": {
            "type": "Click"
        },
        "next": [
            "选择NPC对战开始"
        ],
        "$__mpe_code": {
            "position": {
                "x": -297,
                "y": -33
            }
        }
    },
    "选择NPC对战": {
        "recognition": {
            "type": "OCR",
            "param": {
                "roi": [
                    1062,
                    195,
                    107,
                    39
                ],
                "expected": [
                    "NPC对战"
                ]
            }
        },
        "action": {
            "type": "Click"
        },
        "next": [
            "选择第一位挑战者"
        ],
        "$__mpe_code": {
            "position": {
                "x": 351,
                "y": 302
            }
        }
    },
    "选择第一位挑战者": {
        "recognition": {
            "type": "OCR",
            "param": {
                "roi": [
                    298,
                    94,
                    170,
                    44
                ],
                "expected": [
                    "NPC交战对手"
                ]
            }
        },
        "action": {
            "type": "Click",
            "param": {
                "target_offset": [
                    109,
                    110,
                    0,
                    0
                ]
            }
        },
        "next": [
            "点击挑战"
        ],
        "$__mpe_code": {
            "position": {
                "x": 1167,
                "y": 691
            }
        }
    },
    "点击挑战": {
        "recognition": {
            "type": "OCR",
            "param": {
                "roi": [
                    614,
                    642,
                    55,
                    37
                ],
                "expected": [
                    "挑战"
                ]
            }
        },
        "action": {
            "type": "Click"
        },
        "post_delay": 7000,
        "next": [
            "剩余挑战次数检查节点"
        ],
        "$__mpe_code": {
            "position": {
                "x": 928,
                "y": 208
            }
        }
    },
    "检查是否快速对战": {
        "recognition": {
            "type": "TemplateMatch",
            "param": {
                "roi": [
                    776,
                    631,
                    140,
                    64
                ],
                "template": [
                    "竞技场快速对战.png"
                ]
            }
        },
        "post_delay": 2000,
        "next": [
            "点击快速对战"
        ],
        "$__mpe_code": {
            "position": {
                "x": 1608,
                "y": -592
            }
        }
    },
    "点击快速对战": {
        "recognition": {
            "type": "OCR",
            "param": {
                "roi": [
                    798,
                    643,
                    93,
                    34
                ],
                "expected": [
                    "快速对战"
                ]
            }
        },
        "action": {
            "type": "Click"
        },
        "repeat": 2,
        "post_delay": 8000,
        "next": [
            "确认对战结果",
            "是否有未携带装备弹窗节点"
        ],
        "$__mpe_code": {
            "position": {
                "x": 1903,
                "y": -217
            }
        }
    },
    "确认对战结果": {
        "recognition": {
            "type": "OCR",
            "param": {
                "roi": [
                    713,
                    618,
                    61,
                    36
                ],
                "expected": [
                    "确认"
                ]
            }
        },
        "action": {
            "type": "Click"
        },
        "post_delay": 6000,
        "next": [
            "选择第一位挑战者"
        ],
        "$__mpe_code": {
            "position": {
                "x": 2466,
                "y": 48
            }
        }
    },
    "检查剩余挑战次数": {
        "recognition": {
            "type": "OCR",
            "param": {
                "roi": [
                    712,
                    646,
                    61,
                    35
                ],
                "expected": [
                    "1/0"
                ]
            }
        },
        "post_delay": 2000,
        "next": [
            "结束竞技场返回"
        ],
        "$__mpe_code": {
            "position": {
                "x": 829,
                "y": -415
            }
        }
    },
    "结束竞技场返回": {
        "recognition": {
            "type": "TemplateMatch",
            "param": {
                "roi": [
                    9,
                    10,
                    57,
                    49
                ],
                "template": [
                    "返回箭头.png"
                ]
            }
        },
        "action": {
            "type": "Click"
        },
        "post_delay": 3000,
        "next": [
            "结束竞技场返回二次"
        ],
        "$__mpe_code": {
            "position": {
                "x": 2398,
                "y": 795
            }
        }
    },
    "结束竞技场返回二次": {
        "recognition": {
            "type": "TemplateMatch",
            "param": {
                "roi": [
                    9,
                    10,
                    57,
                    49
                ],
                "template": [
                    "返回箭头.png"
                ]
            }
        },
        "action": {
            "type": "Click"
        },
        "post_delay": 7000,
        "next": [
            "竞技场任务已结束等待主界面"
        ],
        "$__mpe_code": {
            "position": {
                "x": 2686,
                "y": 680
            }
        }
    },
    "处理段位改变弹窗": {
        "recognition": {
            "type": "OCR",
            "param": {
                "roi": [
                    596,
                    520,
                    91,
                    95
                ],
                "expected": [
                    "点击关闭"
                ]
            }
        },
        "action": {
            "type": "Click"
        },
        "next": [
            "选择NPC对战"
        ],
        "$__mpe_code": {
            "position": {
                "x": 42,
                "y": 692
            }
        }
    },
    "剩余挑战次数检查节点": {
        "next": [
            "检查剩余挑战次数"
        ],
        "on_error": [
            "检查是否是快速战斗节点"
        ],
        "$__mpe_code": {
            "position": {
                "x": 820,
                "y": -13
            }
        }
    },
    "是否有未携带装备弹窗节点": {
        "next": [
            "有未携带装备弹窗"
        ],
        "on_error": [
            "确认对战结果"
        ],
        "$__mpe_code": {
            "position": {
                "x": 2146,
                "y": -304
            }
        }
    },
    "有未携带装备弹窗": {
        "recognition": {
            "type": "TemplateMatch",
            "param": {
                "roi": [
                    492,
                    125,
                    283,
                    58
                ],
                "template": [
                    "竞技场未携带装备弹窗.png"
                ]
            }
        },
        "action": {
            "type": "Click",
            "param": {
                "target": [
                    784,
                    528,
                    142,
                    52
                ]
            }
        },
        "post_delay": 6000,
        "next": [
            "确认对战结果"
        ],
        "$__mpe_code": {
            "position": {
                "x": 2460,
                "y": -432
            }
        }
    },
    "检查是否是快速战斗节点": {
        "next": [
            "检查是否快速对战"
        ],
        "on_error": [
            "结束竞技场返回"
        ],
        "$__mpe_code": {
            "position": {
                "x": 1253,
                "y": -509
            }
        }
    },
    "竞技场任务已结束等待主界面": {
        "$__mpe_code": {
            "position": {
                "x": 3028,
                "y": 677
            }
        }
    },
    "进入竞技场选择": {
        "next": [
            "进入竞技场选择开始"
        ],
        "on_error": [
            "找不到竞技场尝试回到主界面"
        ],
        "$__mpe_code": {
            "position": {
                "x": -1701,
                "y": 285
            }
        }
    },
    "进入新手竞技场开始": {
        "next": [
            "进入新手竞技场"
        ],
        "$__mpe_code": {
            "position": {
                "x": -763,
                "y": 157
            }
        }
    },
    "选择NPC对战开始": {
        "next": [
            "选择NPC对战"
        ],
        "on_error": [
            "是不是段位变化"
        ],
        "$__mpe_code": {
            "position": {
                "x": -13,
                "y": 120
            }
        }
    },
    "是不是段位变化": {
        "next": [
            "处理段位改变弹窗"
        ],
        "on_error": [
            "是不是每周奖励待领取"
        ],
        "$__mpe_code": {
            "position": {
                "x": -313,
                "y": 562
            }
        }
    },
    "是不是每周奖励待领取": {
        "recognition": {
            "type": "TemplateMatch",
            "param": {
                "roi": [
                    470,
                    330,
                    191,
                    133
                ],
                "template": [
                    "天空石竞技场待领取.png"
                ]
            }
        },
        "action": {
            "type": "Click"
        },
        "post_delay": 7000,
        "next": [
            "领取每周奖励"
        ],
        "$__mpe_code": {
            "position": {
                "x": -36,
                "y": 935
            }
        }
    },
    "领取每周奖励": {
        "recognition": {
            "type": "OCR",
            "param": {
                "roi": [
                    483,
                    502,
                    340,
                    60
                ],
                "expected": [
                    "领取"
                ]
            }
        },
        "action": {
            "type": "Click"
        },
        "next": [
            "选择NPC对战"
        ],
        "$__mpe_code": {
            "position": {
                "x": 344,
                "y": 949
            }
        }
    },
    "检测是不是每周结算时间": {
        "next": [
            "是每周结算时间直接进入人机挑战"
        ],
        "on_error": [
            "进入新手竞技场开始"
        ],
        "$__mpe_code": {
            "position": {
                "x": -907,
                "y": -120
            }
        }
    },
    "是每周结算时间直接进入人机挑战": {
        "recognition": {
            "type": "OCR",
            "param": {
                "roi": [
                    237,
                    447,
                    233,
                    61
                ],
                "expected": [
                    "NPC对战"
                ]
            }
        },
        "action": {
            "type": "Click"
        },
        "next": [
            "选择第一位挑战者"
        ],
        "$__mpe_code": {
            "position": {
                "x": -518,
                "y": -316
            }
        }
    },
    "未在主界面执行一次退出": {
        "recognition": {
            "type": "TemplateMatch",
            "param": {
                "roi": [
                    2,
                    1,
                    142,
                    60
                ],
                "template": [
                    "返回箭头.png"
                ]
            }
        },
        "action": {
            "type": "Click"
        },
        "next": [
            "进入竞技场选择开始"
        ],
        "$__mpe_code": {
            "position": {
                "x": -932,
                "y": 354
            }
        }
    },
    "找不到竞技场尝试回到主界面": {
        "next": [
            "未在主界面执行一次退出"
        ],
        "$__mpe_code": {
            "position": {
                "x": -1312,
                "y": 369
            }
        }
    }
}