{
    "$__mpe_config_领取活跃度奖励": {
        "$__mpe_code": {
            "prefix": "",
            "coordinateMode": "absolute-v1",
            "lastSyncTime": 1780491486342,
            "isModifiedExternally": false,
            "filePath": "D:\\Application\\Automate\\E7\\assets\\resource\\pipeline\\领取活跃度奖励.json",
            "savedViewport": {
                "x": -194,
                "y": 301,
                "zoom": 0.57
            },
            "filename": "领取活跃度奖励",
            "version": "v1.6.0"
        }
    },
    "收取活跃度100奖励": {
        "recognition": {
            "type": "OCR",
            "param": {
                "roi": [
                    1156,
                    142,
                    44,
                    21
                ],
                "expected": [
                    "100"
                ]
            }
        },
        "action": {
            "type": "Click",
            "param": {
                "target_offset": [
                    0,
                    -51,
                    0,
                    0
                ]
            }
        },
        "next": [
            "检查是否有活跃度弹窗"
        ],
        "$__mpe_code": {
            "position": {
                "x": 979,
                "y": -154
            }
        }
    },
    "检查是否有活跃度弹窗": {
        "recognition": {
            "type": "OCR",
            "param": {
                "roi": [
                    0,
                    0,
                    0,
                    0
                ],
                "expected": [
                    "获得"
                ]
            }
        },
        "next": [
            "返回主界面开始"
        ],
        "$__mpe_code": {
            "position": {
                "x": 1328,
                "y": -40
            }
        }
    },
    "点击每日任务": {
        "recognition": {
            "type": "OCR",
            "param": {
                "roi": [
                    115,
                    125,
                    97,
                    27
                ],
                "expected": [
                    "日记"
                ]
            }
        },
        "action": {
            "type": "Click"
        },
        "next": [
            "收取活跃度100奖励"
        ],
        "$__mpe_code": {
            "position": {
                "x": 572,
                "y": -109
            }
        }
    },
    "进入活跃度界面": {
        "recognition": {
            "type": "FeatureMatch",
            "param": {
                "roi": [
                    919,
                    110,
                    67,
                    56
                ],
                "template": [
                    "日常任务.png"
                ]
            }
        },
        "action": {
            "type": "Click"
        },
        "post_delay": 5000,
        "next": [
            "点击每日任务",
            "进入选择菜单前等待"
        ],
        "$__mpe_code": {
            "position": {
                "x": 219,
                "y": -55
            }
        }
    },
    "进入选择菜单": {
        "recognition": {
            "type": "TemplateMatch",
            "param": {
                "roi": [
                    1217,
                    8,
                    49,
                    50
                ],
                "template": [
                    "主界面特征.png"
                ]
            }
        },
        "action": {
            "type": "Click"
        },
        "next": [
            "进入活跃度界面"
        ],
        "$__mpe_code": {
            "position": {
                "x": -151,
                "y": -148
            }
        }
    },
    "进入选择菜单前等待": {
        "post_delay": 5000,
        "next": [
            "进入选择菜单"
        ],
        "$__mpe_code": {
            "position": {
                "x": -487,
                "y": -3
            }
        }
    },
    "$__mpe_external_返回主界面开始_领取活跃度奖励": {
        "$__mpe_code": {
            "position": {
                "x": 1767,
                "y": 43
            }
        }
    }
}